agile/__init__.py
agile/app.py
agile/core.py
agile/git.py
agile/utils.py
agile/version.py
agile/actions/__init__.py
agile/actions/when.py
agile/bitbucket/__init__.py
agile/commands/__init__.py
agile/commands/agile.py
agile/github/__init__.py
agile/github/components.py
agile/github/releases.py
agile/github/repo.py
agile/plugins/__init__.py
agile/plugins/docs.py
agile/plugins/github.py
agile/plugins/httpcopy.py
agile/plugins/labels.py
agile/plugins/python.py
agile/plugins/s3.py
agile/plugins/sass.py
agile/plugins/shell.py
agile/plugins/tasks.py
agile/plugins/template.py
agile/plugins/vars.py
agile/plugins/watch.py
pulsar_agile-0.5.0.dist-info/DESCRIPTION.rst
pulsar_agile-0.5.0.dist-info/LICENSE.txt
pulsar_agile-0.5.0.dist-info/METADATA
pulsar_agile-0.5.0.dist-info/RECORD
pulsar_agile-0.5.0.dist-info/WHEEL
pulsar_agile-0.5.0.dist-info/metadata.json
pulsar_agile-0.5.0.dist-info/top_level.txt
