Metadata-Version: 2.0
Name: pulsar-agile
Version: 0.5.0
Summary: Python toolkit for agile release managing, building and issue tracking
Home-page: https://github.com/quantmind/pulsar-agile
Author: Luca Sbardella
Author-email: luca@quantmind.com
License: BSD
Platform: UNKNOWN
Classifier: Development Status :: 3 - Alpha
Classifier: Intended Audience :: Developers
Classifier: License :: OSI Approved :: BSD License
Classifier: Operating System :: OS Independent
Classifier: Programming Language :: Python
Classifier: Programming Language :: Python :: 3
Classifier: Programming Language :: Python :: 3.5
Classifier: Programming Language :: Python :: 3.6
Classifier: Topic :: Utilities
Classifier: Topic :: Software Development :: Libraries :: Python Modules
Requires-Dist: jinja2
Requires-Dist: sphinx
Requires-Dist: glob2
Requires-Dist: pulsar-cloud
